xmp/main.py
xmp-0.0.1.dist-info/entry_points.txt
xmp-0.0.1.dist-info/LICENSE
xmp-0.0.1.dist-info/WHEEL
xmp-0.0.1.dist-info/METADATA
xmp-0.0.1.dist-info/RECORD
